django_lockdown-5.0.0.dist-info/licenses/AUTHORS.rst
django_lockdown-5.0.0.dist-info/licenses/LICENSE.txt
lockdown/__init__.py
lockdown/decorators.py
lockdown/forms.py
lockdown/middleware.py
lockdown/templates/lockdown/base.html
lockdown/templates/lockdown/form.html
django_lockdown-5.0.0.dist-info/METADATA
django_lockdown-5.0.0.dist-info/WHEEL
django_lockdown-5.0.0.dist-info/top_level.txt
django_lockdown-5.0.0.dist-info/RECORD
